anenvconf/__init__.py
anenvconf/config.py
anenvconf/exceptions.py
anenvconf-1.0.2.dist-info/LICENSE
anenvconf-1.0.2.dist-info/METADATA
anenvconf-1.0.2.dist-info/WHEEL
anenvconf-1.0.2.dist-info/top_level.txt
anenvconf-1.0.2.dist-info/RECORD
