Metadata-Version: 2.1
Name: anenvconf
Version: 1.0.2
Summary: Module for defining a config schema and importing it from environment variables.
Home-page: https://github.com/anttin/anenvconf
Author: anttin
Author-email: muut.py@antion.fi
License: UNKNOWN
Platform: UNKNOWN
Classifier: Programming Language :: Python :: 3
Classifier: License :: OSI Approved :: MIT License
Classifier: Operating System :: OS Independent
